[
  {
    "info": {
      "serviceURL": "http://136.186.108.110:8080/thermostat/current/value/get?id={}",
      "ontClass": "<http://schema.org/Thing>",
      "graph": "<http://schema.org>",
      "name": "Themostart",
      "description": "Thermostat",
      "resultTag": null,
      "params": [
        {
          "name": "{}",
          "g": "<http://schema.org>",
          "class": "<http://schema.org/Thing>",
          "term": [
            {
              "subject": "http://schema.org/identifier",
              "range": [
                "http://schema.org/Text",
                "http://schema.org/PropertyValue",
                "http://schema.org/URL"
              ],
              "label": "identifier"
            }
          ],
          "value": "1",
          "key": 0,
          "termParent": "http://schema.org/Text"
        }
      ]
    },
    "sla": {
      "cache": false,
      "cost": {
        "unit": "aud",
        "value": 0
      },
      "updateFrequency": {
        "unit": "s",
        "value": 120
      },
      "autoFetch": true,
      "freshness": {
        "unit": "s",
        "value": 120
      },
      "key": [
        "identifier"
      ]
    },
    "attributes": [
      {
        "key": {
          "subject": "http://schema.org/identifier",
          "range": [
            "http://schema.org/Text",
            "http://schema.org/PropertyValue",
            "http://schema.org/URL"
          ],
          "label": "identifier"
        },
        "value": "$id",
        "GeoJson": false,
        "hasValue": true,
        "sampleValue": 1
      },
      {
        "key": {
          "subject": "http://schema.org/additionalType",
          "range": "http://schema.org/URL",
          "label": "additionalType"
        },
        "value": "$value",
        "GeoJson": false,
        "hasValue": true,
        "sampleValue": 27
      }
    ]
  },
  {
    "info":{
      "serviceURL": "http://localhost:5000/carparks?id={}",
      "ontClass": "<http://schema.org/ParkingFacility>",
      "graph": "<http://schema.org>",
      "name": "Carpark",
      "description": "Carpark",
      "resultTag": null,
      "params": [
        {
          "name": "{}",
          "g": "<http://schema.org>",
          "class": "<http://schema.org/Thing>",
          "term": [
            {
              "subject": "http://schema.org/identifier",
              "range": [
                "http://schema.org/Text",
                "http://schema.org/PropertyValue",
                "http://schema.org/URL"
              ],
              "label": "id"
            }
          ],
          "value": "abscd",
          "key": 0,
          "termParent": "http://schema.org/Text"
        }
      ]
    },
    "sla":{
      "cache": true,
      "cost": {
        "unit": "aud",
        "value": 0.2
      },
      "updateFrequency":{
        "unit": "s",
        "value": 60
      },
      "autoFetch": true,
      "freshness": {
        "unit": "s",
        "value": 60
      },
      "key": [
        "id"
      ]
    },
    "attributes":[
      {
        "key": {
          "subject": "http://schema.org/identifier",
          "range": [
            "http://schema.org/Text",
            "http://schema.org/PropertyValue",
            "http://schema.org/URL"
          ],
          "label": "id"
        },
        "value": "&reference",
        "GeoJson": false,
        "hasValue": true,
        "sampleValue": "abcd"
      },
      {
        "key": {
          "subject": "http://schema.org/GeoCoordinates",
          "range": [
            "http://schema.org/address",
            "http://schema.org/latitude",
            "http://schema.org/longitude"
          ],
          "label": "location"
        },
        "value": "&primary_location",
        "GeoJson": false,
        "hasValue": true,
        "sampleValue": 1
      },
      {
        "key": {
          "subject": "http://schema.org/owns",
          "range": [
            "http://schema.org/OwnershipInfo",
            "http://schema.org/Product"
          ],
          "label": "owns"
        },
        "value": "&ownedBy",
        "GeoJson": false,
        "hasValue": true,
        "sampleValue": 1
      },
      {
        "key": {
          "subject": "http://schema.org/currenciesAccepted",
          "range": [
            "http://schema.org/Text"
          ],
          "label": "currenciesAccepted"
        },
        "value": "&currenciesAccepted",
        "GeoJson": false,
        "hasValue": true,
        "sampleValue": 1
      },
      {
        "key": {
          "subject": "http://schema.org/ratingValue",
          "range": [
            "http://schema.org/Text",
            "http://schema.org/Number"
          ],
          "label": "rating"
        },
        "value": "&rating",
        "GeoJson": false,
        "hasValue": true,
        "sampleValue": 1
      },
      {
        "key": {
          "subject": "http://schema.org/DataType",
          "range": [
            "http://schema.org/Boolean"
          ],
          "label": "isOpen"
        },
        "value": "&is_open",
        "GeoJson": false,
        "hasValue": true,
        "sampleValue": 1
      },
      {
        "key": {
          "subject": "http://schema.org/DataType",
          "range": [
            "http://schema.org/Number"
          ],
          "label": "availabileSlots"
        },
        "value": "&free_slots",
        "GeoJson": false,
        "hasValue": true,
        "sampleValue": 1
      },
      {
        "key": {
          "subject": "http://schema.org/height",
          "range": [
            "http://schema.org/Distance",
            "http://schema.org/QuantitativeValue"
          ],
          "label": "maxHeight"
        },
        "value": "&maxHeight",
        "GeoJson": false,
        "hasValue": true,
        "sampleValue": 1
      },
      {
        "key": {
          "subject": "http://schema.org/Intangible",
          "range": [
            "http://schema.org/Offer"
          ],
          "label": "price"
        },
        "value": "&price_offer",
        "GeoJson": false,
        "hasValue": true,
        "sampleValue": 1
      },
      {
        "key": {
          "subject": "http://schema.org/name",
          "range": [
            "http://schema.org/Text"
          ],
          "label": "name"
        },
        "value": "&name",
        "GeoJson": false,
        "hasValue": true,
        "sampleValue": "name"
      }
    ]
  },
  {
    "info":{
      "serviceURL": "http://localhost:5000/places?name={}",
      "ontClass": "<http://schema.org/Place>",
      "graph": "<http://schema.org>",
      "name": "Place",
      "description": "Place",
      "resultTag": null,
      "params": [
        {
          "name": "{}",
          "g": "<http://schema.org>",
          "class": "<http://schema.org/Thing>",
          "term": [
            {
              "subject": "http://schema.org/name",
              "range": [
                "http://schema.org/Text"
              ],
              "label": "name"
            }
          ],
          "value": "SkyDeck",
          "key": 0,
          "termParent": "http://schema.org/Text"
        }
      ]
    },
    "sla":{
      "cache": true,
      "cost": {
        "unit": "aud",
        "value": 0.5
      },
      "updateFrequency":{
        "unit": "s",
        "value": 3600
      },
      "autoFetch": true,
      "freshness": {
        "unit": "s",
        "value": 3600
      },
      "key": [
        "name",
        "identifier"
      ]
    },
    "attributes":[
      {
        "key": {
          "subject": "http://schema.org/name",
          "range": [
            "http://schema.org/Text"

          ],
          "label": "name"
        },
        "value": "&name",
        "GeoJson": false,
        "hasValue": true,
        "sampleValue": "Melbourne Skydeck"
      },
      {
        "key": {
          "subject": "http://schema.org/identifier",
          "range": [
            "http://schema.org/Text",
            "http://schema.org/PropertyValue",
            "http://schema.org/URL"
          ],
          "label": "identifier"
        },
        "value": "&reference",
        "GeoJson": false,
        "hasValue": true,
        "sampleValue": "ChIJQffkhK1C1moR3Z0-w-t8SS8"
      },
      {
        "key": {
          "subject": "http://schema.org/address",
          "range": [
            "http://schema.org/Text",
            "http://schema.org/PostalAddress"

          ],
          "label": "address"
        },
        "value": "&formatted_address",
        "GeoJson": false,
        "hasValue": true,
        "sampleValue": "7 Riverside Quay, Southbank VIC 3006, Australia"
      },
      {
        "key": {
          "subject": "http://schema.org/GeoCoordinates",
          "range": [
            "http://schema.org/address",
            "http://schema.org/latitude",
            "http://schema.org/longitude"
          ],
          "label": "location"
        },
        "value": "&primary_location",
        "GeoJson": false,
        "hasValue": true,
        "sampleValue": 1
      }
    ]
  },
  {
    "info":{
      "serviceURL": "http://localhost:5000/vehicles?vin={}",
      "ontClass": "<http://schema.org/Vehicle>",
      "graph": "<http://schema.org>",
      "name": "Vehicle",
      "description": "Vehicle",
      "resultTag": null,
      "params": [
        {
          "name": "{}",
          "g": "<http://schema.org>",
          "class": "<http://schema.org/Thing>",
          "term": [
            {
              "subject": "http://schema.org/identifier",
              "range": [
                "http://schema.org/Text",
                "http://schema.org/PropertyValue",
                "http://schema.org/URL"
              ],
              "label": "vin"
            }
          ],
          "value": "C335DBB3B31248F986B99CBBBAE1E064",
          "key": 0,
          "termParent": "http://schema.org/Text"
        }
      ]
    },
    "sla":{
      "cache": true,
      "cost": {
        "unit": "aud",
        "value": 0.6
      },
      "updateFrequency":{
        "unit": "s",
        "value": 60
      },
      "autoFetch": true,
      "freshness": {
        "unit": "s",
        "value": 60
      },
      "key": [
        "vin"
      ]
    },
    "attributes":[
      {
        "key": {
          "subject": "http://schema.org/identifier",
          "range": [
            "http://schema.org/Text",
            "http://schema.org/PropertyValue",
            "http://schema.org/URL"
          ],
          "label": "vin"
        },
        "value": "&vin",
        "GeoJson": false,
        "hasValue": true,
        "sampleValue": "C335DBB3B31248F986B99CBBBAE1E064"
      },
      {
        "key": {
          "subject": "http://schema.org/name",
          "range": [
            "http://schema.org/Text"
          ],
          "label": "make"
        },
        "value": "&make",
        "GeoJson": false,
        "hasValue": true,
        "sampleValue": "alfa-romero"
      },
      {
        "key": {
          "subject": "http://schema.org/wheelbase",
          "range": [
            "http://schema.org/QuantitativeValue"

          ],
          "label": "wheelBase"
        },
        "value": "&wheel-base",
        "GeoJson": false,
        "hasValue": true,
        "sampleValue": 88.6
      },
      {
        "key": {
          "subject": "http://schema.org/height",
          "range": [
            "http://schema.org/Distance",
            "http://schema.org/QuantitativeValue"

          ],
          "label": "height"
        },
        "value": "&height",
        "GeoJson": false,
        "hasValue": true,
        "sampleValue": 1.67
      },
      {
        "key": {
          "subject": "http://schema.org/length",
          "range": [
            "http://schema.org/Distance",
            "http://schema.org/QuantitativeValue"

          ],
          "label": "length"
        },
        "value": "&length",
        "GeoJson": false,
        "hasValue": true,
        "sampleValue": 1.67
      },
      {
        "key": {
          "subject": "http://schema.org/width",
          "range": [
            "http://schema.org/Distance",
            "http://schema.org/QuantitativeValue"

          ],
          "label": "width"
        },
        "value": "&width",
        "GeoJson": false,
        "hasValue": true,
        "sampleValue": 1.67
      },
      {
        "key": {
          "subject": "http://schema.org/fuelEfficiency",
          "range": [
            "http://schema.org/QuantitativeValue"
          ],
          "label": "fuelEfficiency"
        },
        "value": "&performance",
        "GeoJson": false,
        "hasValue": true,
        "sampleValue": 49.39515
      },
      {
        "key": {
          "subject": "http://schema.org/speed",
          "range": [
            "http://schema.org/QuantitativeValue"
          ],
          "label": "speed"
        },
        "value": "&speed",
        "GeoJson": false,
        "hasValue": true,
        "sampleValue": 49.39515
      }
    ]
  },
  {
    "info":{
      "serviceURL": "http://localhost:5000/weather?location={}",
      "ontClass": "<http://schema.org/Thing>",
      "graph": "<http://schema.org>",
      "name": "Weather",
      "description": "Weather",
      "resultTag": null,
      "params": [
        {
          "name": "{}",
          "g": "<http://schema.org>",
          "class": "<http://schema.org/Thing>",
          "term": [
            {
              "subject": "http://schema.org/identifier",
              "range": [
                "http://schema.org/Text",
                "http://schema.org/PropertyValue",
                "http://schema.org/URL"
              ],
              "label": "location"
            }
          ],
          "value": "Melbourne,Australia",
          "key": 0,
          "termParent": "http://schema.org/Text"
        }
      ]
    },
    "sla":{
      "cache": true,
      "cost": {
        "unit": "aud",
        "value": 0.1
      },
      "updateFrequency":{
        "unit": "s",
        "value": 3600
      },
      "autoFetch": true,
      "freshness": {
        "unit": "s",
        "value": 3600
      },
      "key": []
    },
    "attributes":[
      {
        "key": {
          "subject": "http://schema.org/StructuredValue",
          "range": [
            "http://schema.org/QuantitativeValue"
          ],
          "label": "temperature"
        },
        "value": "&temperature",
        "GeoJson": false,
        "hasValue": true,
        "sampleValue": 10
      },
      {
        "key": {
          "subject": "http://schema.org/address",
          "range": [
            "http://schema.org/Text",
            "http://schema.org/PostalAddress"
          ],
          "label": "location"
        },
        "value": "&location",
        "GeoJson": false,
        "hasValue": true,
        "sampleValue": "Melbourne,Australia"
      },
      {
        "key": {
          "subject": "http://schema.org/StructuredValue",
          "range": [
            "http://schema.org/QuantitativeValue"
          ],
          "label": "precipitation"
        },
        "value": "&precipitation",
        "GeoJson": false,
        "hasValue": true,
        "sampleValue": 27
      },
      {
        "key": {
          "subject": "http://schema.org/StructuredValue",
          "range": [
            "http://schema.org/QuantitativeValue"
          ],
          "label": "windGust"
        },
        "value": "&wind_gust",
        "GeoJson": false,
        "hasValue": true,
        "sampleValue": 27
      },
      {
        "key": {
          "subject": "http://schema.org/StructuredValue",
          "range": [
            "http://schema.org/QuantitativeValue"
          ],
          "label": "windSpeed"
        },
        "value": "&wind_speed",
        "GeoJson": false,
        "hasValue": true,
        "sampleValue": 27
      },
      {
        "key": {
          "subject": "http://schema.org/StructuredValue",
          "range": [
            "http://schema.org/QuantitativeValue"
          ],
          "label": "windDirection"
        },
        "value": "&wind_direction",
        "GeoJson": false,
        "hasValue": true,
        "sampleValue": 27
      },
      {
        "key": {
          "subject": "http://schema.org/StructuredValue",
          "range": [
            "http://schema.org/QuantitativeValue"
          ],
          "label": "uvIndex"
        },
        "value": "&uvIndex",
        "GeoJson": false,
        "hasValue": true,
        "sampleValue": 27
      },
      {
        "key": {
          "subject": "http://schema.org/StructuredValue",
          "range": [
            "http://schema.org/QuantitativeValue"
          ],
          "label": "directRadiation"
        },
        "value": "&direct_radiation",
        "GeoJson": false,
        "hasValue": true,
        "sampleValue": 27
      },
      {
        "key": {
          "subject": "http://schema.org/StructuredValue",
          "range": [
            "http://schema.org/QuantitativeValue"
          ],
          "label": "pressure"
        },
        "value": "&mean_sea_level_presssure",
        "GeoJson": false,
        "hasValue": true,
        "sampleValue": 27
      }
    ]
  }
]